FWeb/App.py
FWeb/Http.py
FWeb/Utils.py
FWeb/__init__.py
FWeb-0.2.dist-info/METADATA
FWeb-0.2.dist-info/WHEEL
FWeb-0.2.dist-info/top_level.txt
FWeb-0.2.dist-info/RECORD
