Metadata-Version: 2.1
Name: FWeb
Version: 0.2
Summary: A simple Web Framework
Home-page: https://github.com/zhshch2002/FWeb
Author: zhshch
Author-email: zhshch2002@outlook.com
License: UNKNOWN
Platform: UNKNOWN
Requires-Dist: jinja2
